gate_manager/__init__.py
gate_manager/connection.py
gate_manager/gate.py
gate_manager/sweeper.py
gate_manager-2.8.1.dist-info/METADATA
gate_manager-2.8.1.dist-info/WHEEL
gate_manager-2.8.1.dist-info/licenses/LICENSE
gate_manager-2.8.1.dist-info/RECORD
