Metadata-Version: 2.4
Name: gate-manager
Version: 2.8.1
Summary: A package for controlling and managing gate voltages in quantum devices.
Project-URL: Homepage, https://github.com/chenx820/gate-manager
Project-URL: Repository, https://github.com/chenx820/gate-manager.git
Author-email: Chen Huang <chen.huang23@imperial.ac.uk>
License: MIT
License-File: LICENSE
Classifier: License :: OSI Approved :: MIT License
Classifier: Operating System :: OS Independent
Classifier: Programming Language :: Python :: 3
Requires-Python: >=3.6
Requires-Dist: conductorquantum
Requires-Dist: matplotlib
Requires-Dist: nanonis-tramea>=1.0.6
Requires-Dist: numpy
Requires-Dist: tqdm
